bananalyzer/__init__.py
bananalyzer/__main__.py
bananalyzer/__version.py
bananalyzer/data/__init__.py
bananalyzer/data/example_detail_schemas.py
bananalyzer/data/example_fetching.py
bananalyzer/data/example_s3.py
bananalyzer/data/example_schemas.py
bananalyzer/hooks.py
bananalyzer/junit.py
bananalyzer/runner/__init__.py
bananalyzer/runner/agent_runner.py
bananalyzer/runner/evals.py
bananalyzer/runner/generator.py
bananalyzer/runner/null_agent_wrapper.py
bananalyzer/runner/runner.py
bananalyzer/runner/website_responder.py
bananalyzer/schema.py
bananalyzer-0.12.0.dist-info/LICENSE
bananalyzer-0.12.0.dist-info/METADATA
bananalyzer-0.12.0.dist-info/WHEEL
bananalyzer-0.12.0.dist-info/entry_points.txt
bananalyzer-0.12.0.dist-info/RECORD
