Metadata-Version: 2.1
Name: bananalyzer
Version: 0.12.0
Summary: Open source AI Agent evaluation framework for web tasks 🐒🍌
Author: asim-shrestha
Author-email: asim.shrestha@hotmail.com
Requires-Python: >=3.11,<4.0
Classifier: Programming Language :: Python :: 3
Classifier: Programming Language :: Python :: 3.11
Classifier: Programming Language :: Python :: 3.12
Classifier: Programming Language :: Python :: 3.13
Requires-Dist: boto3 (>=1.35.8,<2.0.0)
Requires-Dist: deepdiff (>=8.0.0,<9.0.0)
Requires-Dist: numpy (>=2.1.0,<3.0.0)
Requires-Dist: playwright (>=1.47.0)
Requires-Dist: psutil (>=6.0.0,<7.0.0)
Requires-Dist: pydantic (>=2.8.2,<3.0.0)
Requires-Dist: pytest (>=8.3.2,<9.0.0)
Requires-Dist: pytest-asyncio (>=0.24.0,<0.25.0)
Requires-Dist: pytest-html (>=4.1.1,<5.0.0)
Requires-Dist: pytest-xdist (>=3.6.1,<4.0.0)
Requires-Dist: requests (>=2.32.3,<3.0.0)
Requires-Dist: tabulate (>=0.9.0,<0.10.0)
